KeyboardGate/KeyboardGate.py
KeyboardGate/__init__.py
keyboardgate-0.0.2.dist-info/METADATA
keyboardgate-0.0.2.dist-info/WHEEL
keyboardgate-0.0.2.dist-info/licenses/LICENSE
keyboardgate-0.0.2.dist-info/RECORD
